periorbital/__init__.py
periorbital/extract_periorbital_distances.py
periorbital/find_anatomy_from_masks.py
periorbital/main.py
periorbital/periorbital_plotter.py
periorbital/pkg_utils.py
periorbital/segment_eyes.py
periorbital_package-0.1.3.dist-info/METADATA
periorbital_package-0.1.3.dist-info/WHEEL
periorbital_package-0.1.3.dist-info/top_level.txt
periorbital_package-0.1.3.dist-info/RECORD
