Metadata-Version: 2.1
Name: periorbital-package
Version: 0.1.3
Summary: A package for periorbital distance segmentation and measurement.
Home-page: https://github.com/monkeygobah/periorbital_package
Author: Georgie Nahass
Author-email: gnahas2@uic.edu
Classifier: Programming Language :: Python :: 3
Classifier: License :: OSI Approved :: MIT License
Classifier: Operating System :: OS Independent
Requires-Python: >=3.8
Requires-Dist: torch >=1.9.0
Requires-Dist: torchvision >=0.10.0
Requires-Dist: huggingface-hub
Requires-Dist: numpy >=1.19.2
Requires-Dist: scipy >=1.5.2
Requires-Dist: matplotlib >=3.3.2
Requires-Dist: opencv-python >=4.5.1
Requires-Dist: scikit-learn >=0.24.2
Requires-Dist: pillow >=8.0.1
Requires-Dist: pandas >=1.1.3
Requires-Dist: mediapipe >=0.8.6
